zsp_arl_eval/__build_num__.py
zsp_arl_eval/__init__.py
zsp_arl_eval/__version__.py
zsp_arl_eval/core.cpython-310-x86_64-linux-gnu.so
zsp_arl_eval/libzsp-arl-eval.so
zsp_arl_eval/pkginfo.py
zsp_arl_eval/share/include/zsp/arl/eval/FactoryExt.h
zsp_arl_eval/share/include/zsp/arl/eval/IBuiltinFuncInfo.h
zsp_arl_eval/share/include/zsp/arl/eval/IComponentTreeData.h
zsp_arl_eval/share/include/zsp/arl/eval/IEval.h
zsp_arl_eval/share/include/zsp/arl/eval/IEvalBackend.h
zsp_arl_eval/share/include/zsp/arl/eval/IEvalContext.h
zsp_arl_eval/share/include/zsp/arl/eval/IEvalContextActivity.h
zsp_arl_eval/share/include/zsp/arl/eval/IEvalContextInt.h
zsp_arl_eval/share/include/zsp/arl/eval/IEvalFunctionData.h
zsp_arl_eval/share/include/zsp/arl/eval/IEvalListener.h
zsp_arl_eval/share/include/zsp/arl/eval/IEvalStackFrame.h
zsp_arl_eval/share/include/zsp/arl/eval/IEvalThread.h
zsp_arl_eval/share/include/zsp/arl/eval/IEvalThreadEventListener.h
zsp_arl_eval/share/include/zsp/arl/eval/IEvalThreadId.h
zsp_arl_eval/share/include/zsp/arl/eval/IEvalValProvider.h
zsp_arl_eval/share/include/zsp/arl/eval/IFactory.h
zsp_arl_eval/share/include/zsp/arl/eval/IModelAddressSpace.h
zsp_arl_eval/share/include/zsp/arl/eval/IModelEvaluator.h
zsp_arl_eval/share/include/zsp/arl/eval/impl/EvalBackendBase.h
zsp_arl_eval/share/include/zsp/arl/eval/impl/EvalListenerBase.h
zsp_arl_eval/share/include/zsp/arl/eval/impl/TaskEvalGetLval.h
zuspec_arl_eval-0.0.5.dist-info/LICENSE
zuspec_arl_eval-0.0.5.dist-info/METADATA
zuspec_arl_eval-0.0.5.dist-info/WHEEL
zuspec_arl_eval-0.0.5.dist-info/entry_points.txt
zuspec_arl_eval-0.0.5.dist-info/top_level.txt
zuspec_arl_eval-0.0.5.dist-info/RECORD
