Metadata-Version: 2.2
Name: zuspec-arl-eval
Version: 0.0.5
Summary: Core ARL data model library
Home-page: https://github.com/zuspec/zuspec-arl-eval
Author: Matthew Ballance
Author-email: matt.ballance@gmail.com
License: Apache 2.0
Keywords: SystemVerilog,Verilog,RTL,Python
License-File: LICENSE
Requires-Dist: debug-mgr
Requires-Dist: pyapi-compat-if
Requires-Dist: vsc-dm
Requires-Dist: vsc-solvers
Requires-Dist: zuspec-arl-dm
Dynamic: author
Dynamic: author-email
Dynamic: description
Dynamic: home-page
Dynamic: keywords
Dynamic: license
Dynamic: requires-dist
Dynamic: summary
